sagemaker_knockout/__init__.py
sagemaker_knockout/__main__.py
sagemaker_knockout/knockout.py
sagemaker_knockout-0.0.7.dist-info/LICENSE
sagemaker_knockout-0.0.7.dist-info/METADATA
sagemaker_knockout-0.0.7.dist-info/WHEEL
sagemaker_knockout-0.0.7.dist-info/top_level.txt
sagemaker_knockout-0.0.7.dist-info/RECORD
